pixivSpiderCreatedByHanXu/__init__.py
pixivSpiderCreatedByHanXu-0.0.7.dist-info/LICENSE
pixivSpiderCreatedByHanXu-0.0.7.dist-info/METADATA
pixivSpiderCreatedByHanXu-0.0.7.dist-info/WHEEL
pixivSpiderCreatedByHanXu-0.0.7.dist-info/top_level.txt
pixivSpiderCreatedByHanXu-0.0.7.dist-info/RECORD
